joselogs/__init__.py
joselogs/logger.py
joselogs/pyarmor_runtime_000000/__init__.py
obfuscated_joselogs/__init__.py
obfuscated_joselogs/logger.py
obfuscated_joselogs/pyarmor_runtime_000000/__init__.py
joselogs-0.7.dist-info/METADATA
joselogs-0.7.dist-info/WHEEL
joselogs-0.7.dist-info/top_level.txt
joselogs-0.7.dist-info/RECORD
