Metadata-Version: 2.1
Name: joselogs
Version: 0.7
Summary: A simple logger with sum functionality
Home-page: https://github.com/seunome/joselogs
Author: Jose Eduardo
Author-email: josedumoura@gmail.com
Classifier: Programming Language :: Python :: 3
Classifier: License :: OSI Approved :: MIT License
Classifier: Operating System :: OS Independent
Requires-Python: >=3.6
